muse2wfdb/converter.py
muse2wfdb-1.2.0.dist-info/licenses/LICENSE
muse2wfdb-1.2.0.dist-info/METADATA
muse2wfdb-1.2.0.dist-info/WHEEL
muse2wfdb-1.2.0.dist-info/top_level.txt
muse2wfdb-1.2.0.dist-info/RECORD
