Metadata-Version: 2.4
Name: muse2wfdb
Version: 1.2.0
Summary: Convert GE MUSE ECG XML exports to WFDB format
Author: Levente Nagy
License: MIT
Project-URL: Homepage, https://github.com/nagyl1999/muse2wfdb
Project-URL: Issues, https://github.com/nagyl1999/muse2wfdb/issues
Requires-Python: >=3.8
License-File: LICENSE
Requires-Dist: wfdb>=4.1.0
Requires-Dist: xmltodict>=0.13.0
Requires-Dist: numpy>=1.22
Dynamic: license-file
